debandshit/__init__.py
debandshit/debanders.py
debandshit/f3kdb.py
debandshit/placebo.py
debandshit/py.typed
vs_debandshit-0.4.5.dist-info/LICENSE
vs_debandshit-0.4.5.dist-info/METADATA
vs_debandshit-0.4.5.dist-info/WHEEL
vs_debandshit-0.4.5.dist-info/top_level.txt
vs_debandshit-0.4.5.dist-info/RECORD
