Metadata-Version: 2.1
Name: vs-debandshit
Version: 0.4.5
Summary: VapourSynth Debanding Functions Collection
Home-page: https://github.com/LightArrowsEXE/debandshit
Author: LightArrowsEXE
Author-email: Lightarrowsreboot@gmail.com
License: UNKNOWN
Platform: UNKNOWN
Classifier: Programming Language :: Python :: 3
Classifier: License :: OSI Approved :: MIT License
Classifier: Operating System :: OS Independent
Requires-Python: >=3.9
License-File: LICENSE
Requires-Dist: VapourSynth (>=51)
Requires-Dist: vsutil (>=0.5.0)
